setup.cfg
setup.py
dynComLogin/__init__.py
dynComLogin/__main__.py
dynComLogin.egg-info/PKG-INFO
dynComLogin.egg-info/SOURCES.txt
dynComLogin.egg-info/dependency_links.txt
dynComLogin.egg-info/entry_points.txt
dynComLogin.egg-info/not-zip-safe
dynComLogin.egg-info/requires.txt
dynComLogin.egg-info/top_level.txt