Metadata-Version: 1.0
Name: dynComLogin
Version: 0.1
Summary: log in to dyn.com
Home-page: UNKNOWN
Author: Thomas Schilz
Author-email: thschilz @at@ web .dot. de
License: UNKNOWN
Platform: UNKNOWN
